prime/__init__.py
prime/prime.py
primechecker-1.0.0.dist-info/METADATA
primechecker-1.0.0.dist-info/WHEEL
primechecker-1.0.0.dist-info/top_level.txt
primechecker-1.0.0.dist-info/RECORD
