Metadata-Version: 2.1
Name: primechecker
Version: 1.0.0
Summary: A package for checking prime numbers
Author: Titus K.
Author-email: tituskamunya@gmail.com
